{
    "timestamp": "2026-04-19 02:25:55",
    "fund_name": "伯克希爾·哈撒韋 (BRK.B) 13F 持倉 (Q1 2026)",
    "total_value": 424.3,
    "cash_ratio": 163.49,
    "top_10_ratio": 89.34,
    "quarterly_change": 3.6,
    "holdings": [
        {
            "symbol": "AAPL",
            "value": 141.58,
            "change": -2.39
        },
        {
            "symbol": "BAC",
            "value": 51.1,
            "change": -1.46
        },
        {
            "symbol": "KO",
            "value": 25.76,
            "change": 1.94
        },
        {
            "symbol": "AMZN",
            "value": 15.23,
            "change": 2.22
        },
        {
            "symbol": "AXP",
            "value": 8.57,
            "change": 2.61
        },
        {
            "symbol": "CVX",
            "value": 5.72,
            "change": 2.1
        },
        {
            "symbol": "OXY",
            "value": 5.05,
            "change": 4.95
        },
        {
            "symbol": "MCO",
            "value": 2.4,
            "change": -1.91
        },
        {
            "symbol": "VRSN",
            "value": 1.12,
            "change": 1.75
        },
        {
            "symbol": "HPQ",
            "value": 1.93,
            "change": -0.05
        }
    ]
}