{
    "timestamp": "2026-01-10 01:22:52",
    "funds": [
        {
            "symbol": "VFIAX",
            "latest_price": NaN,
            "daily_change_percent": 0.0,
            "date": "2026-01-09"
        },
        {
            "symbol": "VTSAX",
            "latest_price": NaN,
            "daily_change_percent": 0.0,
            "date": "2026-01-09"
        },
        {
            "symbol": "VBTLX",
            "latest_price": NaN,
            "daily_change_percent": 0.0,
            "date": "2026-01-09"
        },
        {
            "symbol": "BIL",
            "latest_price": 91.47000122070312,
            "daily_change_percent": 0.021874546887357127,
            "date": "2026-01-09"
        }
    ]
}